Workbook

Sheet Summary
A1: Simple Bank (Lite) - Findings & Insights
A2: PostgreSQL project | 4 tables, 11 queries, 1 safe transfer | Fictional data, pre-transfer snapshot | All figures in Rs and formula-driven
A4: Key metric | B4: Value | C4: How it is calculated
A5: Customers | B5: =COUNTA(Customers!A:A)-1 -> 8 | C5: Rows in customers
A6: Accounts | B6: =COUNTA(Accounts!A:A)-1 -> 10 | C6: Rows in accounts
A7: Total balances (Rs) | B7: =SUM(Accounts!D:D) -> 1410000 | C7: Q4
A8: Average balance per account (Rs) | B8: =AVERAGE(Accounts!D:D) -> 141000 | C8: Q4
A9: Total deposits (Rs) | B9: =SUMIFS(Transactions!D:D,Transactions!C:C,"DEPOSIT") -> 485000 | C9: Q5
A10: Total withdrawals (Rs) | B10: =SUMIFS(Transactions!D:D,Transactions!C:C,"WITHDRAWAL") -> 144000 | C10: Q5
A11: Net inflow (Rs) | B11: =B9-B10 -> 341000 | C11: Deposits - withdrawals
A12: Total loan book (Rs) | B12: =SUM(Loans!C:C) -> 6700000 | C12: Sum of loans.amount
A13: Defaulted loans (Rs) | B13: =SUMIFS(Loans!C:C,Loans!D:D,"DEFAULTED") -> 200000 | C13: Loans with status DEFAULTED
A14: Default rate (by value) | B14: =IF(B12=0,0,B13/B12) -> 0.029850746 | C14: Defaulted / total loan book
A15: Customers with a loan | B15: =COUNTIF('Customer Analysis'!L5:L12,">0") -> 4 | C15: Q10
A16: Dormant customers (0 txns) | B16: =COUNTIF('Customer Analysis'!H5:H12,0) -> 1 | C16: Q9
A17: Largest customer share of balances | B17: =MAX('Customer Analysis'!F5:F12) -> 0.38297872 | C17: Q7 basis
A18: Loan book / total balances (x) | B18: =IF(B7=0,0,B12/B7) -> 4.751773 | C18: Illustrative on sample data
A20: Key insights
A21: Theme | B21: Finding | C21: Evidence (live from data) | D21: Suggested action (analyst view)
A22: Deposit concentration | B22: Balances are concentrated in a few customers; the largest holder is a CURRENT account customer. | C22: =INDEX('Customer Analysis'!$B$5:$B$12,MATCH(1,'Customer Analysis'!$G$5:$G$12,0))&" holds "&TEXT(MAX('Customer Analysis'!$F$5:$F$12),"0.0%")&" of all balances; the top 3 customers hold "&TEXT(SUMIFS('Customer Analysis'!$E$5:$E$12,'Customer Analysis'!$G$5:$G$12,"<=3")/'Customer Analysis'!$E$13,"0.0%")&"." -> Vikram Singh holds 38.3% of all balances; the top 3 customers hold 76.2%. | D22: Assign relationship managers to top holders; monitor concentration risk.
A23: Cash-flow health | B23: Deposits exceed withdrawals, so the book is a net inflow. | C23: ="Deposits Rs "&TEXT(B9,"#,##0")&" vs withdrawals Rs "&TEXT(B10,"#,##0")&": net inflow Rs "&TEXT(B11,"#,##0")&" ("&TEXT(B10/B9,"0.0%")&" of deposits withdrawn)." -> Deposits Rs 485,000 vs withdrawals Rs 144,000: net inflow Rs 341,000 (29.7% of deposits withdrawn). | D23: Track the withdrawal ratio monthly as an early liquidity signal.
A24: Multi-account customers | B24: Rohan Mehta (savings + current) and Karan Malhotra (two savings) hold two accounts each. | C24: =COUNTIF('Customer Analysis'!$D$5:$D$12,">1")&" of "&B5&" customers hold more than one account." -> 2 of 8 customers hold more than one account. | D24: Offer a consolidated view and relationship pricing.
A25: Dormant balance | B25: Meera Joshi has an account with no transactions at all (found with LEFT JOIN + IS NULL). | C25: ="Rs "&TEXT(SUMIFS('Customer Analysis'!$E$5:$E$12,'Customer Analysis'!$H$5:$H$12,0),"#,##0")&" sits with "&B16&" dormant customer(s)." -> Rs 38,000 sits with 1 dormant customer(s). | D25: Re-engagement outreach: digital onboarding, FD or SIP offers.
A26: Loan-book concentration | B26: One customer's loan dominates the loan book. | C26: ="Largest loan is Rs "&TEXT(MAX('Customer Analysis'!$L$5:$L$12),"#,##0")&" = "&TEXT(MAX('Customer Analysis'!$L$5:$L$12)/B12,"0.0%")&" of the loan book." -> Largest loan is Rs 4,000,000 = 59.7% of the loan book. | D26: Set single-borrower exposure limits and review the largest exposures.
A27: Customer leverage | B27: Rohan Mehta's loan is far above his deposits in this bank. | C27: ="Highest loan-to-balance: "&INDEX('Customer Analysis'!$B$5:$B$12,MATCH(MAX('Customer Analysis'!$N$5:$N$12),'Customer Analysis'!$N$5:$N$12,0))&" at "&TEXT(MAX('Customer Analysis'!$N$5:$N$12),"0.0")&"x (flag threshold "&TEXT(Notes!$B$6,"0.0")&"x)." -> Highest loan-to-balance: Rohan Mehta at 13.1x (flag threshold 5.0x). | D27: Add to a watch-list; check repayment capacity and collateral.
A28: Credit risk | B28: Karan Malhotra's Rs 2 lakh loan is DEFAULTED and his deposits cover little of it. | C28: ="Defaulted Rs "&TEXT(B13,"#,##0")&" = "&TEXT(B14,"0.0%")&" of loan book; the defaulter holds Rs "&TEXT(SUMIFS('Customer Analysis'!$E$5:$E$12,'Customer Analysis'!$M$5:$M$12,">0"),"#,##0")&" in deposits ("&TEXT(SUMIFS('Customer Analysis'!$E$5:$E$12,'Customer Analysis'!$M$5:$M$12,">0")/B13,"0.0%")&" cover)." -> Defaulted Rs 200,000 = 3.0% of loan book; the defaulter holds Rs 23,000 in deposits (11.5% cover). | D28: Recovery workflow; consider lien on deposits where terms allow.
A29: Geographic skew | B29: Mumbai carries a disproportionate share of loans compared with its share of customers. | C29: ="Mumbai: "&TEXT(INDEX('City Analysis'!$G$5:$G$9,MATCH("Mumbai",'City Analysis'!$A$5:$A$9,0)),"0.0%")&" of loans vs "&TEXT(INDEX('City Analysis'!$C$5:$C$9,MATCH("Mumbai",'City Analysis'!$A$5:$A$9,0)),"0.0%")&" of customers." -> Mumbai: 59.7% of loans vs 25.0% of customers. | D29: Monitor city-level exposure; diversify lending across branches.
A30: Cross-sell opportunity | B30: Several customers with healthy balances have no loan product. | C30: =COUNTIF('Customer Analysis'!$L$5:$L$12,0)&" customers have no loan, holding Rs "&TEXT(SUMIFS('Customer Analysis'!$E$5:$E$12,'Customer Analysis'!$L$5:$L$12,0),"#,##0")&" in balances (includes the dormant customer)." -> 4 customers have no loan, holding Rs 312,000 in balances (includes the dormant customer). | D30: Targeted pre-approved loan or investment offers (subject to credit checks).

Sheet Customer Analysis
A1: Customer Analysis
A2: One row per customer, built from the raw tabs with formulas. Amounts in Rs. Snapshot before transfer demo.
A4: customer_id | B4: Name | C4: City | D4: # Accounts | E4: Total balance | F4: Share of bank balances | G4: Balance rank | H4: # Txns | I4: Deposits | J4: Withdrawals | K4: Net flow | L4: Loan amount | M4: Defaulted amount | N4: Loan-to-balance (x) | O4: Flag
A5: =Customers!A2 -> 1 | B5: =Customers!B2 -> Rohan Mehta | C5: =Customers!C2 -> Mumbai | D5: =COUNTIF(Accounts!$B:$B,$A5) -> 2 | E5: =SUMIFS(Accounts!$D:$D,Accounts!$B:$B,$A5) -> 305000 | F5: =E5/$E$13 -> 0.21631206 | G5: =RANK(E5,$E$5:$E$12) -> 2 | H5: =COUNTIF(Transactions!$F:$F,$A5) -> 3 | I5: =SUMIFS(Transactions!$D:$D,Transactions!$F:$F,$A5,Transactions!$C:$C,"DEPOSIT") -> 32000 | J5: =SUMIFS(Transactions!$D:$D,Transactions!$F:$F,$A5,Transactions!$C:$C,"WITHDRAWAL") -> 5000 | K5: =I5-J5 -> 27000 | L5: =SUMIFS(Loans!$C:$C,Loans!$B:$B,$A5) -> 4000000 | M5: =SUMIFS(Loans!$C:$C,Loans!$B:$B,$A5,Loans!$D:$D,"DEFAULTED") -> 0 | N5: =IF(E5=0,0,L5/E5) -> 13.114754 | O5: =IF(H5=0,"Dormant - re-engage",IF(M5>0,"Default - recovery focus",IF(N5>Notes!$B$6,"High leverage - monitor",IF(L5=0,"No loan - cross-sell","Standard")))) -> High leverage - monitor
A6: =Customers!A3 -> 2 | B6: =Customers!B3 -> Ananya Iyer | C6: =Customers!C3 -> Chennai | D6: =COUNTIF(Accounts!$B:$B,$A6) -> 1 | E6: =SUMIFS(Accounts!$D:$D,Accounts!$B:$B,$A6) -> 82000 | F6: =E6/$E$13 -> 0.058156028 | G6: =RANK(E6,$E$5:$E$12) -> 5 | H6: =COUNTIF(Transactions!$F:$F,$A6) -> 2 | I6: =SUMIFS(Transactions!$D:$D,Transactions!$F:$F,$A6,Transactions!$C:$C,"DEPOSIT") -> 30000 | J6: =SUMIFS(Transactions!$D:$D,Transactions!$F:$F,$A6,Transactions!$C:$C,"WITHDRAWAL") -> 7000 | K6: =I6-J6 -> 23000 | L6: =SUMIFS(Loans!$C:$C,Loans!$B:$B,$A6) -> 0 | M6: =SUMIFS(Loans!$C:$C,Loans!$B:$B,$A6,Loans!$D:$D,"DEFAULTED") -> 0 | N6: =IF(E6=0,0,L6/E6) -> 0 | O6: =IF(H6=0,"Dormant - re-engage",IF(M6>0,"Default - recovery focus",IF(N6>Notes!$B$6,"High leverage - monitor",IF(L6=0,"No loan - cross-sell","Standard")))) -> No loan - cross-sell
A7: =Customers!A4 -> 3 | B7: =Customers!B4 -> Karan Malhotra | C7: =Customers!C4 -> Delhi | D7: =COUNTIF(Accounts!$B:$B,$A7) -> 2 | E7: =SUMIFS(Accounts!$D:$D,Accounts!$B:$B,$A7) -> 23000 | F7: =E7/$E$13 -> 0.016312057 | G7: =RANK(E7,$E$5:$E$12) -> 8 | H7: =COUNTIF(Transactions!$F:$F,$A7) -> 3 | I7: =SUMIFS(Transactions!$D:$D,Transactions!$F:$F,$A7,Transactions!$C:$C,"DEPOSIT") -> 23000 | J7: =SUMIFS(Transactions!$D:$D,Transactions!$F:$F,$A7,Transactions!$C:$C,"WITHDRAWAL") -> 2000 | K7: =I7-J7 -> 21000 | L7: =SUMIFS(Loans!$C:$C,Loans!$B:$B,$A7) -> 200000 | M7: =SUMIFS(Loans!$C:$C,Loans!$B:$B,$A7,Loans!$D:$D,"DEFAULTED") -> 200000 | N7: =IF(E7=0,0,L7/E7) -> 8.6956522 | O7: =IF(H7=0,"Dormant - re-engage",IF(M7>0,"Default - recovery focus",IF(N7>Notes!$B$6,"High leverage - monitor",IF(L7=0,"No loan - cross-sell","Standard")))) -> Default - recovery focus
A8: =Customers!A5 -> 4 | B8: =Customers!B5 -> Priya Nair | C8: =Customers!C5 -> Bengaluru | D8: =COUNTIF(Accounts!$B:$B,$A8) -> 1 | E8: =SUMIFS(Accounts!$D:$D,Accounts!$B:$B,$A8) -> 230000 | F8: =E8/$E$13 -> 0.16312057 | G8: =RANK(E8,$E$5:$E$12) -> 3 | H8: =COUNTIF(Transactions!$F:$F,$A8) -> 2 | I8: =SUMIFS(Transactions!$D:$D,Transactions!$F:$F,$A8,Transactions!$C:$C,"DEPOSIT") -> 50000 | J8: =SUMIFS(Transactions!$D:$D,Transactions!$F:$F,$A8,Transactions!$C:$C,"WITHDRAWAL") -> 10000 | K8: =I8-J8 -> 40000 | L8: =SUMIFS(Loans!$C:$C,Loans!$B:$B,$A8) -> 500000 | M8: =SUMIFS(Loans!$C:$C,Loans!$B:$B,$A8,Loans!$D:$D,"DEFAULTED") -> 0 | N8: =IF(E8=0,0,L8/E8) -> 2.173913 | O8: =IF(H8=0,"Dormant - re-engage",IF(M8>0,"Default - recovery focus",IF(N8>Notes!$B$6,"High leverage - monitor",IF(L8=0,"No loan - cross-sell","Standard")))) -> Standard
A9: =Customers!A6 -> 5 | B9: =Customers!B6 -> Vikram Singh | C9: =Customers!C6 -> Delhi | D9: =COUNTIF(Accounts!$B:$B,$A9) -> 1 | E9: =SUMIFS(Accounts!$D:$D,Accounts!$B:$B,$A9) -> 540000 | F9: =E9/$E$13 -> 0.38297872 | G9: =RANK(E9,$E$5:$E$12) -> 1 | H9: =COUNTIF(Transactions!$F:$F,$A9) -> 2 | I9: =SUMIFS(Transactions!$D:$D,Transactions!$F:$F,$A9,Transactions!$C:$C,"DEPOSIT") -> 250000 | J9: =SUMIFS(Transactions!$D:$D,Transactions!$F:$F,$A9,Transactions!$C:$C,"WITHDRAWAL") -> 100000 | K9: =I9-J9 -> 150000 | L9: =SUMIFS(Loans!$C:$C,Loans!$B:$B,$A9) -> 2000000 | M9: =SUMIFS(Loans!$C:$C,Loans!$B:$B,$A9,Loans!$D:$D,"DEFAULTED") -> 0 | N9: =IF(E9=0,0,L9/E9) -> 3.7037037 | O9: =IF(H9=0,"Dormant - re-engage",IF(M9>0,"Default - recovery focus",IF(N9>Notes!$B$6,"High leverage - monitor",IF(L9=0,"No loan - cross-sell","Standard")))) -> Standard
A10: =Customers!A7 -> 6 | B10: =Customers!B7 -> Sneha Kulkarni | C10: =Customers!C7 -> Pune | D10: =COUNTIF(Accounts!$B:$B,$A10) -> 1 | E10: =SUMIFS(Accounts!$D:$D,Accounts!$B:$B,$A10) -> 67000 | F10: =E10/$E$13 -> 0.04751773 | G10: =RANK(E10,$E$5:$E$12) -> 6 | H10: =COUNTIF(Transactions!$F:$F,$A10) -> 1 | I10: =SUMIFS(Transactions!$D:$D,Transactions!$F:$F,$A10,Transactions!$C:$C,"DEPOSIT") -> 40000 | J10: =SUMIFS(Transactions!$D:$D,Transactions!$F:$F,$A10,Transactions!$C:$C,"WITHDRAWAL") -> 0 | K10: =I10-J10 -> 40000 | L10: =SUMIFS(Loans!$C:$C,Loans!$B:$B,$A10) -> 0 | M10: =SUMIFS(Loans!$C:$C,Loans!$B:$B,$A10,Loans!$D:$D,"DEFAULTED") -> 0 | N10: =IF(E10=0,0,L10/E10) -> 0 | O10: =IF(H10=0,"Dormant - re-engage",IF(M10>0,"Default - recovery focus",IF(N10>Notes!$B$6,"High leverage - monitor",IF(L10=0,"No loan - cross-sell","Standard")))) -> No loan - cross-sell
A11: =Customers!A8 -> 7 | B11: =Customers!B8 -> Arjun Reddy | C11: =Customers!C8 -> Bengaluru | D11: =COUNTIF(Accounts!$B:$B,$A11) -> 1 | E11: =SUMIFS(Accounts!$D:$D,Accounts!$B:$B,$A11) -> 125000 | F11: =E11/$E$13 -> 0.088652482 | G11: =RANK(E11,$E$5:$E$12) -> 4 | H11: =COUNTIF(Transactions!$F:$F,$A11) -> 2 | I11: =SUMIFS(Transactions!$D:$D,Transactions!$F:$F,$A11,Transactions!$C:$C,"DEPOSIT") -> 60000 | J11: =SUMIFS(Transactions!$D:$D,Transactions!$F:$F,$A11,Transactions!$C:$C,"WITHDRAWAL") -> 20000 | K11: =I11-J11 -> 40000 | L11: =SUMIFS(Loans!$C:$C,Loans!$B:$B,$A11) -> 0 | M11: =SUMIFS(Loans!$C:$C,Loans!$B:$B,$A11,Loans!$D:$D,"DEFAULTED") -> 0 | N11: =IF(E11=0,0,L11/E11) -> 0 | O11: =IF(H11=0,"Dormant - re-engage",IF(M11>0,"Default - recovery focus",IF(N11>Notes!$B$6,"High leverage - monitor",IF(L11=0,"No loan - cross-sell","Standard")))) -> No loan - cross-sell
A12: =Customers!A9 -> 8 | B12: =Customers!B9 -> Meera Joshi | C12: =Customers!C9 -> Mumbai | D12: =COUNTIF(Accounts!$B:$B,$A12) -> 1 | E12: =SUMIFS(Accounts!$D:$D,Accounts!$B:$B,$A12) -> 38000 | F12: =E12/$E$13 -> 0.026950355 | G12: =RANK(E12,$E$5:$E$12) -> 7 | H12: =COUNTIF(Transactions!$F:$F,$A12) -> 0 | I12: =SUMIFS(Transactions!$D:$D,Transactions!$F:$F,$A12,Transactions!$C:$C,"DEPOSIT") -> 0 | J12: =SUMIFS(Transactions!$D:$D,Transactions!$F:$F,$A12,Transactions!$C:$C,"WITHDRAWAL") -> 0 | K12: =I12-J12 -> 0 | L12: =SUMIFS(Loans!$C:$C,Loans!$B:$B,$A12) -> 0 | M12: =SUMIFS(Loans!$C:$C,Loans!$B:$B,$A12,Loans!$D:$D,"DEFAULTED") -> 0 | N12: =IF(E12=0,0,L12/E12) -> 0 | O12: =IF(H12=0,"Dormant - re-engage",IF(M12>0,"Default - recovery focus",IF(N12>Notes!$B$6,"High leverage - monitor",IF(L12=0,"No loan - cross-sell","Standard")))) -> Dormant - re-engage
A13: Total | D13: =SUM(D5:D12) -> 10 | E13: =SUM(E5:E12) -> 1410000 | F13: =SUM(F5:F12) -> 1 | H13: =SUM(H5:H12) -> 15 | I13: =SUM(I5:I12) -> 485000 | J13: =SUM(J5:J12) -> 144000 | K13: =SUM(K5:K12) -> 341000 | L13: =SUM(L5:L12) -> 6700000 | M13: =SUM(M5:M12) -> 200000 | N13: =IF(E13=0,0,L13/E13) -> 4.751773

Sheet City Analysis
A1: City Analysis
A2: Roll-up of Customer Analysis by city. Loan totals equal Q11 output.
A4: City | B4: # Customers | C4: Share of customers | D4: Total balance | E4: Share of balances | F4: Loan amount | G4: Share of loans | H4: Loan-to-balance (x) | I4: Defaulted amount
A5: Mumbai | B5: =COUNTIF(Customers!$C:$C,$A5) -> 2 | C5: =B5/$B$10 -> 0.25 | D5: =SUMIFS('Customer Analysis'!$E$5:$E$12,'Customer Analysis'!$C$5:$C$12,$A5) -> 343000 | E5: =D5/$D$10 -> 0.24326241 | F5: =SUMIFS('Customer Analysis'!$L$5:$L$12,'Customer Analysis'!$C$5:$C$12,$A5) -> 4000000 | G5: =F5/$F$10 -> 0.59701493 | H5: =IF(D5=0,0,F5/D5) -> 11.661808 | I5: =SUMIFS('Customer Analysis'!$M$5:$M$12,'Customer Analysis'!$C$5:$C$12,$A5) -> 0
A6: Delhi | B6: =COUNTIF(Customers!$C:$C,$A6) -> 2 | C6: =B6/$B$10 -> 0.25 | D6: =SUMIFS('Customer Analysis'!$E$5:$E$12,'Customer Analysis'!$C$5:$C$12,$A6) -> 563000 | E6: =D6/$D$10 -> 0.39929078 | F6: =SUMIFS('Customer Analysis'!$L$5:$L$12,'Customer Analysis'!$C$5:$C$12,$A6) -> 2200000 | G6: =F6/$F$10 -> 0.32835821 | H6: =IF(D6=0,0,F6/D6) -> 3.9076377 | I6: =SUMIFS('Customer Analysis'!$M$5:$M$12,'Customer Analysis'!$C$5:$C$12,$A6) -> 200000
A7: Bengaluru | B7: =COUNTIF(Customers!$C:$C,$A7) -> 2 | C7: =B7/$B$10 -> 0.25 | D7: =SUMIFS('Customer Analysis'!$E$5:$E$12,'Customer Analysis'!$C$5:$C$12,$A7) -> 355000 | E7: =D7/$D$10 -> 0.25177305 | F7: =SUMIFS('Customer Analysis'!$L$5:$L$12,'Customer Analysis'!$C$5:$C$12,$A7) -> 500000 | G7: =F7/$F$10 -> 0.074626866 | H7: =IF(D7=0,0,F7/D7) -> 1.4084507 | I7: =SUMIFS('Customer Analysis'!$M$5:$M$12,'Customer Analysis'!$C$5:$C$12,$A7) -> 0
A8: Chennai | B8: =COUNTIF(Customers!$C:$C,$A8) -> 1 | C8: =B8/$B$10 -> 0.125 | D8: =SUMIFS('Customer Analysis'!$E$5:$E$12,'Customer Analysis'!$C$5:$C$12,$A8) -> 82000 | E8: =D8/$D$10 -> 0.058156028 | F8: =SUMIFS('Customer Analysis'!$L$5:$L$12,'Customer Analysis'!$C$5:$C$12,$A8) -> 0 | G8: =F8/$F$10 -> 0 | H8: =IF(D8=0,0,F8/D8) -> 0 | I8: =SUMIFS('Customer Analysis'!$M$5:$M$12,'Customer Analysis'!$C$5:$C$12,$A8) -> 0
A9: Pune | B9: =COUNTIF(Customers!$C:$C,$A9) -> 1 | C9: =B9/$B$10 -> 0.125 | D9: =SUMIFS('Customer Analysis'!$E$5:$E$12,'Customer Analysis'!$C$5:$C$12,$A9) -> 67000 | E9: =D9/$D$10 -> 0.04751773 | F9: =SUMIFS('Customer Analysis'!$L$5:$L$12,'Customer Analysis'!$C$5:$C$12,$A9) -> 0 | G9: =F9/$F$10 -> 0 | H9: =IF(D9=0,0,F9/D9) -> 0 | I9: =SUMIFS('Customer Analysis'!$M$5:$M$12,'Customer Analysis'!$C$5:$C$12,$A9) -> 0
A10: Total | B10: =SUM(B5:B9) -> 8 | C10: =SUM(C5:C9) -> 1 | D10: =SUM(D5:D9) -> 1410000 | E10: =SUM(E5:E9) -> 1 | F10: =SUM(F5:F9) -> 6700000 | G10: =SUM(G5:G9) -> 1 | H10: =IF(D10=0,0,F10/D10) -> 4.751773 | I10: =SUM(I5:I9) -> 200000
A12: Check: city total balance ties to Accounts tab | F12: =IF(D10=SUM(Accounts!D:D),"OK","MISMATCH") -> OK
A13: Check: city total loans ties to Loans tab | F13: =IF(F10=SUM(Loans!C:C),"OK","MISMATCH") -> OK

Sheet Transfer & Integrity
A1: Safe Money Transfer & Integrity Tests
A2: Part 4 of the script: Rohan (acct 1) sends Rs 10,000 to Ananya (acct 2).
A4: Account | B4: Owner | C4: Before (Rs) | D4: Transfer (Rs) | E4: After COMMIT (Rs) | F4: Source of 'After'
A5: 1 | B5: Rohan Mehta | C5: =INDEX(Accounts!$D:$D,MATCH(A5,Accounts!$A:$A,0)) -> 45000 | D5: -10000 | E5: =C5+D5 -> 35000 | F5: Observed: pgAdmin screenshot shows 35,000.00 for account 1
A6: 2 | B6: Ananya Iyer | C6: =INDEX(Accounts!$D:$D,MATCH(A6,Accounts!$A:$A,0)) -> 82000 | D6: =-D5 -> 10000 | E6: =C6+D6 -> 92000 | F6: Calculated from script logic (not visible in screenshots)
A7: Total | C7: =SUM(C5:C6) -> 127000 | D7: =SUM(D5:D6) -> 0 | E7: =SUM(E5:E6) -> 127000 | F7: =IF(C7=E7,"Money conserved: total unchanged","CHECK") -> Money conserved: total unchanged
A10: Test | B10: What the script does | C10: Expected behaviour | D10: Evidence
A11: Atomic transfer (BEGIN...COMMIT) | B11: Debit account 1 and credit account 2 inside one transaction. | C11: Both updates apply together or neither does. | D11: Account 1 = 35,000 in pgAdmin after the demo.
A12: ROLLBACK demo | B12: Debit account 1 by 10,000, then ROLLBACK. | C12: Debit is undone; balance unchanged. | D12: Account 1 still 35,000 after rollback (screenshot 1, Query complete, 1 row).
A13: Overdraft constraint | B13: Commented-out UPDATE subtracts 99,999,999 from account 1. | C13: Fails: CHECK (balance >= 0) is violated. | D13: Per script comment; not run in the screenshots.

Sheet Data Checks
A1: Data Checks & Design Observations
A2: Findings from reviewing the schema and the data. Useful as 'what I would improve' talking points.
A4: account_id | B4: Account balance | C4: Net txn flow (deposits - withdrawals) | D4: Unexplained (balance - net flow) | E4: # Txns
A5: =Accounts!A2 -> 1 | B5: =Accounts!D2 -> 45000 | C5: =SUMIFS(Transactions!$D:$D,Transactions!$B:$B,A5,Transactions!$C:$C,"DEPOSIT")-SUMIFS(Transactions!$D:$D,Transactions!$B:$B,A5,Transactions!$C:$C,"WITHDRAWAL") -> 15000 | D5: =B5-C5 -> 30000 | E5: =COUNTIF(Transactions!$B:$B,A5) -> 2
A6: =Accounts!A3 -> 2 | B6: =Accounts!D3 -> 82000 | C6: =SUMIFS(Transactions!$D:$D,Transactions!$B:$B,A6,Transactions!$C:$C,"DEPOSIT")-SUMIFS(Transactions!$D:$D,Transactions!$B:$B,A6,Transactions!$C:$C,"WITHDRAWAL") -> 23000 | D6: =B6-C6 -> 59000 | E6: =COUNTIF(Transactions!$B:$B,A6) -> 2
A7: =Accounts!A4 -> 3 | B7: =Accounts!D4 -> 15000 | C7: =SUMIFS(Transactions!$D:$D,Transactions!$B:$B,A7,Transactions!$C:$C,"DEPOSIT")-SUMIFS(Transactions!$D:$D,Transactions!$B:$B,A7,Transactions!$C:$C,"WITHDRAWAL") -> 13000 | D7: =B7-C7 -> 2000 | E7: =COUNTIF(Transactions!$B:$B,A7) -> 2
A8: =Accounts!A5 -> 4 | B8: =Accounts!D5 -> 230000 | C8: =SUMIFS(Transactions!$D:$D,Transactions!$B:$B,A8,Transactions!$C:$C,"DEPOSIT")-SUMIFS(Transactions!$D:$D,Transactions!$B:$B,A8,Transactions!$C:$C,"WITHDRAWAL") -> 40000 | D8: =B8-C8 -> 190000 | E8: =COUNTIF(Transactions!$B:$B,A8) -> 2
A9: =Accounts!A6 -> 5 | B9: =Accounts!D6 -> 540000 | C9: =SUMIFS(Transactions!$D:$D,Transactions!$B:$B,A9,Transactions!$C:$C,"DEPOSIT")-SUMIFS(Transactions!$D:$D,Transactions!$B:$B,A9,Transactions!$C:$C,"WITHDRAWAL") -> 150000 | D9: =B9-C9 -> 390000 | E9: =COUNTIF(Transactions!$B:$B,A9) -> 2
A10: =Accounts!A7 -> 6 | B10: =Accounts!D7 -> 67000 | C10: =SUMIFS(Transactions!$D:$D,Transactions!$B:$B,A10,Transactions!$C:$C,"DEPOSIT")-SUMIFS(Transactions!$D:$D,Transactions!$B:$B,A10,Transactions!$C:$C,"WITHDRAWAL") -> 40000 | D10: =B10-C10 -> 27000 | E10: =COUNTIF(Transactions!$B:$B,A10) -> 1
A11: =Accounts!A8 -> 7 | B11: =Accounts!D8 -> 125000 | C11: =SUMIFS(Transactions!$D:$D,Transactions!$B:$B,A11,Transactions!$C:$C,"DEPOSIT")-SUMIFS(Transactions!$D:$D,Transactions!$B:$B,A11,Transactions!$C:$C,"WITHDRAWAL") -> 40000 | D11: =B11-C11 -> 85000 | E11: =COUNTIF(Transactions!$B:$B,A11) -> 2
A12: =Accounts!A9 -> 8 | B12: =Accounts!D9 -> 38000 | C12: =SUMIFS(Transactions!$D:$D,Transactions!$B:$B,A12,Transactions!$C:$C,"DEPOSIT")-SUMIFS(Transactions!$D:$D,Transactions!$B:$B,A12,Transactions!$C:$C,"WITHDRAWAL") -> 0 | D12: =B12-C12 -> 38000 | E12: =COUNTIF(Transactions!$B:$B,A12) -> 0
A13: =Accounts!A10 -> 9 | B13: =Accounts!D10 -> 260000 | C13: =SUMIFS(Transactions!$D:$D,Transactions!$B:$B,A13,Transactions!$C:$C,"DEPOSIT")-SUMIFS(Transactions!$D:$D,Transactions!$B:$B,A13,Transactions!$C:$C,"WITHDRAWAL") -> 12000 | D13: =B13-C13 -> 248000 | E13: =COUNTIF(Transactions!$B:$B,A13) -> 1
A14: =Accounts!A11 -> 10 | B14: =Accounts!D11 -> 8000 | C14: =SUMIFS(Transactions!$D:$D,Transactions!$B:$B,A14,Transactions!$C:$C,"DEPOSIT")-SUMIFS(Transactions!$D:$D,Transactions!$B:$B,A14,Transactions!$C:$C,"WITHDRAWAL") -> 8000 | D14: =B14-C14 -> 0 | E14: =COUNTIF(Transactions!$B:$B,A14) -> 1
A15: Total | B15: =SUM(B5:B14) -> 1410000 | C15: =SUM(C5:C14) -> 341000 | D15: =SUM(D5:D14) -> 1069000 | E15: =SUM(E5:E14) -> 15
A17: Reading the table
A18: ="Accounts where transaction history does not explain the balance: "&COUNTIF(D5:D14,"<>0")&" of "&COUNTA(A5:A14)&". The schema has no opening-balance field, so balances cannot be rebuilt from the transactions table." -> Accounts where transaction history does not explain the balance: 9 of 10. The schema has no opening-balance field, so balances cannot be rebuilt from the transactions table.
A20: # | B20: Observation | E20: Suggested improvement
A21: 1 | B21: Transfer updates balances but inserts nothing into the transactions table, so the transfer leaves no audit trail. | E21: Insert a DEBIT and a CREDIT row inside the same BEGIN...COMMIT block.
A22: 2 | B22: No opening balance or ledger: balance is a stored number that history cannot reproduce (see table above). | E22: Add an opening-balance transaction per account, or compute balance from the ledger.
A23: 3 | B23: Loans table has no interest rate, tenure, repayment or due-date fields, so default risk cannot be measured beyond a status flag. | E23: Add rate, tenure, EMI and repayment tables.
A24: 4 | B24: Transfer does not lock rows: two simultaneous transfers on one account could interleave. | E24: Use SELECT ... FOR UPDATE on both rows, or a stricter isolation level.
A25: 5 | B25: Foreign-key columns (customer_id, account_id) have no explicit indexes; PostgreSQL does not create them automatically. | E25: Add indexes on FK columns used in joins as data grows.

Sheet Interview Points
A1: Interview Talking Points
A2: Likely questions with answers grounded in this project.
A3: # | B3: Question | C3: Answer (from this project)
A4: 1 | B4: Why did you use a separate schema? | C4: Everything lives in simple_bank, so DROP SCHEMA ... CASCADE resets the project without touching any other data in the database.
A5: 2 | B5: Why NUMERIC(12,2) for money instead of FLOAT? | C5: NUMERIC stores exact decimals, so there are no binary rounding errors in balances or totals.
A6: 3 | B6: How do you stop an account going negative? | C6: CHECK (balance >= 0) on accounts. The constraint test (subtract 99,999,999) fails with a check-constraint violation.
A7: 4 | B7: Why wrap the transfer in a transaction? | C7: Debit and credit must succeed together or not at all. BEGIN...COMMIT makes it atomic; the ROLLBACK demo shows an undo leaves the balance unchanged.
A8: 5 | B8: INNER JOIN vs LEFT JOIN in your queries? | C8: Q6/Q10 use INNER JOIN (only matching rows). Q9 uses LEFT JOIN + IS NULL to find customers with no transactions, which surfaces Meera Joshi.
A9: 6 | B9: WHERE vs HAVING? | C9: WHERE filters rows before grouping; HAVING filters groups after aggregation. Q8 uses HAVING COUNT(*) > 1 to find multi-account customers.
A10: 7 | B10: What business insight stands out? | C10: Balances and loans are concentrated: one customer holds the largest share of deposits, and one Mumbai loan dominates the loan book (see Summary and Customer Analysis tabs).
A11: 8 | B11: What would you improve? | C11: Log transfers in the transactions table, add an opening balance/ledger, add loan rate and repayment data, lock rows during transfers, and index foreign keys (see Data Checks tab).

Sheet Query Log
A1: Query Log (Q1-Q11)
A2: Results verified by running the script's queries on this data (pre-transfer snapshot).
A3: Query | B3: Business question | C3: SQL concept | D3: Result
A4: Q1 | B4: List all customers | C4: SELECT * | D4: 8 customers
A5: Q2 | B5: Customers in Delhi | C5: WHERE | D5: Karan Malhotra, Vikram Singh
A6: Q3 | B6: Accounts above Rs 1,00,000, highest first | C6: WHERE + ORDER BY | D6: Accounts 5, 9, 4, 7 (540,000; 260,000; 230,000; 125,000)
A7: Q4 | B7: Total money, average balance, number of accounts | C7: SUM / AVG / COUNT | D7: Total 1,410,000; average 141,000.00; 10 accounts
A8: Q5 | B8: Total deposits vs withdrawals | C8: GROUP BY | D8: DEPOSIT 485,000 (9 txns); WITHDRAWAL 144,000 (6 txns)
A9: Q6 | B9: Each customer with their accounts | C9: INNER JOIN | D9: 10 rows (one per account)
A10: Q7 | B10: Top 3 customers by total balance | C10: JOIN + GROUP BY + LIMIT | D10: Vikram Singh 540,000; Rohan Mehta 305,000; Priya Nair 230,000
A11: Q8 | B11: Customers with more than one account | C11: GROUP BY + HAVING | D11: Rohan Mehta (2), Karan Malhotra (2)
A12: Q9 | B12: Customers who never transacted | C12: LEFT JOIN + IS NULL | D12: Meera Joshi
A13: Q10 | B13: Customers with loans and status | C13: JOIN | D13: Rohan 4,000,000 ACTIVE; Priya 500,000 ACTIVE; Vikram 2,000,000 ACTIVE; Karan 200,000 DEFAULTED
A14: Q11 | B14: Total loan amount per city | C14: JOIN + GROUP BY | D14: Mumbai 4,000,000; Delhi 2,200,000; Bengaluru 500,000 (matches pgAdmin screenshot)

Sheet Customers
A1: customer_id | B1: name | C1: city | D1: phone
A2: 1 | B2: Rohan Mehta | C2: Mumbai | D2: 9000000001
A3: 2 | B3: Ananya Iyer | C3: Chennai | D3: 9000000002
A4: 3 | B4: Karan Malhotra | C4: Delhi | D4: 9000000003
A5: 4 | B5: Priya Nair | C5: Bengaluru | D5: 9000000004
A6: 5 | B6: Vikram Singh | C6: Delhi | D6: 9000000005
A7: 6 | B7: Sneha Kulkarni | C7: Pune | D7: 9000000006
A8: 7 | B8: Arjun Reddy | C8: Bengaluru | D8: 9000000007
A9: 8 | B9: Meera Joshi | C9: Mumbai | D9: 9000000008

Sheet Accounts
A1: account_id | B1: customer_id | C1: account_type | D1: balance (Rs)
A2: 1 | B2: 1 | C2: SAVINGS | D2: 45000
A3: 2 | B3: 2 | C3: SAVINGS | D3: 82000
A4: 3 | B4: 3 | C4: SAVINGS | D4: 15000
A5: 4 | B5: 4 | C5: SAVINGS | D5: 230000
A6: 5 | B6: 5 | C6: CURRENT | D6: 540000
A7: 6 | B7: 6 | C7: SAVINGS | D7: 67000
A8: 7 | B8: 7 | C8: SAVINGS | D8: 125000
A9: 8 | B9: 8 | C9: SAVINGS | D9: 38000
A10: 9 | B10: 1 | C10: CURRENT | D10: 260000
A11: 10 | B11: 3 | C11: SAVINGS | D11: 8000

Sheet Transactions
A1: txn_id | B1: account_id | C1: txn_type | D1: amount (Rs) | E1: txn_date | F1: customer_id (lookup)
A2: 1 | B2: 1 | C2: DEPOSIT | D2: 20000 | E2: 46205 | F2: =INDEX(Accounts!$B:$B,MATCH(B2,Accounts!$A:$A,0)) -> 1
A3: 2 | B3: 1 | C3: WITHDRAWAL | D3: 5000 | E3: 46213 | F3: =INDEX(Accounts!$B:$B,MATCH(B3,Accounts!$A:$A,0)) -> 1
A4: 3 | B4: 2 | C4: DEPOSIT | D4: 30000 | E4: 46208 | F4: =INDEX(Accounts!$B:$B,MATCH(B4,Accounts!$A:$A,0)) -> 2
A5: 4 | B5: 2 | C5: WITHDRAWAL | D5: 7000 | E5: 46235 | F5: =INDEX(Accounts!$B:$B,MATCH(B5,Accounts!$A:$A,0)) -> 2
A6: 5 | B6: 3 | C6: DEPOSIT | D6: 15000 | E6: 46211 | F6: =INDEX(Accounts!$B:$B,MATCH(B6,Accounts!$A:$A,0)) -> 3
A7: 6 | B7: 3 | C7: WITHDRAWAL | D7: 2000 | E7: 46237 | F7: =INDEX(Accounts!$B:$B,MATCH(B7,Accounts!$A:$A,0)) -> 3
A8: 7 | B8: 4 | C8: DEPOSIT | D8: 50000 | E8: 46239 | F8: =INDEX(Accounts!$B:$B,MATCH(B8,Accounts!$A:$A,0)) -> 4
A9: 8 | B9: 4 | C9: WITHDRAWAL | D9: 10000 | E9: 46254 | F9: =INDEX(Accounts!$B:$B,MATCH(B9,Accounts!$A:$A,0)) -> 4
A10: 9 | B10: 5 | C10: DEPOSIT | D10: 250000 | E10: 46243 | F10: =INDEX(Accounts!$B:$B,MATCH(B10,Accounts!$A:$A,0)) -> 5
A11: 10 | B11: 5 | C11: WITHDRAWAL | D11: 100000 | E11: 46266 | F11: =INDEX(Accounts!$B:$B,MATCH(B11,Accounts!$A:$A,0)) -> 5
A12: 11 | B12: 6 | C12: DEPOSIT | D12: 40000 | E12: 46267 | F12: =INDEX(Accounts!$B:$B,MATCH(B12,Accounts!$A:$A,0)) -> 6
A13: 12 | B13: 7 | C13: DEPOSIT | D13: 60000 | E13: 46268 | F13: =INDEX(Accounts!$B:$B,MATCH(B13,Accounts!$A:$A,0)) -> 7
... A16: 15 | B16: 10 | C16: DEPOSIT | D16: 8000 | E16: 46271 | F16: =INDEX(Accounts!$B:$B,MATCH(B16,Accounts!$A:$A,0)) -> 3

Sheet Loans
A1: loan_id | B1: customer_id | C1: amount (Rs) | D1: status
A2: 1 | B2: 1 | C2: 4000000 | D2: ACTIVE
A3: 2 | B3: 4 | C3: 500000 | D3: ACTIVE
A4: 3 | B4: 5 | C4: 2000000 | D4: ACTIVE
A5: 4 | B5: 3 | C5: 200000 | D5: DEFAULTED

Sheet Notes
A1: Notes & Assumptions
A3: Item | B3: Detail
A4: Data source | B4: Fictional sample data from simple_bank_lite_postgres.sql (loaded as-is). Raw tabs: Customers, Accounts, Transactions, Loans.
A5: Snapshot | B5: All analysis uses the seed data BEFORE the Rs 10,000 transfer demo (Rohan's account 1 = 45,000; Ananya's account 2 = 82,000). The transfer is shown separately on 'Transfer & Integrity'.
A6: High-leverage threshold (x) | B6: 5
A7: Threshold basis | B7: Analyst-chosen cut-off for flagging loan-to-balance ratio; NOT from the project script or any ICICI policy. Change cell B5 and flags update.
A8: Loan-to-balance ratio | B8: Customer's total loan amount / customer's total account balance in this dataset. Illustrative only, not a regulatory ratio.
A9: Helper column | B9: Transactions!F looks up customer_id from account_id so transactions can be rolled up per customer.
A10: Query results | B10: Query Log results were verified by running the script's queries against this data; Q11 also matches the pgAdmin output screenshot provided.
